odoo/addons/l10n_br_fiscal_edi/README.rst
odoo/addons/l10n_br_fiscal_edi/__init__.py
odoo/addons/l10n_br_fiscal_edi/__manifest__.py
odoo/addons/l10n_br_fiscal_edi/i18n/l10n_br_fiscal_edi.pot
odoo/addons/l10n_br_fiscal_edi/i18n/pt_BR.po
odoo/addons/l10n_br_fiscal_edi/models/__init__.py
odoo/addons/l10n_br_fiscal_edi/models/document.py
odoo/addons/l10n_br_fiscal_edi/models/document_event.py
odoo/addons/l10n_br_fiscal_edi/models/document_workflow.py
odoo/addons/l10n_br_fiscal_edi/models/invalidate_number.py
odoo/addons/l10n_br_fiscal_edi/readme/CONTRIBUTORS.rst
odoo/addons/l10n_br_fiscal_edi/readme/DESCRIPTION.rst
odoo/addons/l10n_br_fiscal_edi/readme/ROADMAP.rst
odoo/addons/l10n_br_fiscal_edi/readme/USAGE.rst
odoo/addons/l10n_br_fiscal_edi/security/ir.model.access.csv
odoo/addons/l10n_br_fiscal_edi/static/description/icon.png
odoo/addons/l10n_br_fiscal_edi/static/description/index.html
odoo/addons/l10n_br_fiscal_edi/tests/__init__.py
odoo/addons/l10n_br_fiscal_edi/tests/test_fiscal_document_generic.py
odoo/addons/l10n_br_fiscal_edi/tests/test_tax_benefit.py
odoo/addons/l10n_br_fiscal_edi/tests/test_workflow.py
odoo/addons/l10n_br_fiscal_edi/views/document_event_report.xml
odoo/addons/l10n_br_fiscal_edi/views/document_event_template.xml
odoo/addons/l10n_br_fiscal_edi/views/document_event_view.xml
odoo/addons/l10n_br_fiscal_edi/views/document_view.xml
odoo/addons/l10n_br_fiscal_edi/views/invalidate_number_view.xml
odoo/addons/l10n_br_fiscal_edi/views/l10n_br_fiscal_action.xml
odoo/addons/l10n_br_fiscal_edi/views/l10n_br_fiscal_menu.xml
odoo/addons/l10n_br_fiscal_edi/wizards/__init__.py
odoo/addons/l10n_br_fiscal_edi/wizards/base_wizard_mixin.py
odoo/addons/l10n_br_fiscal_edi/wizards/document_cancel_wizard.py
odoo/addons/l10n_br_fiscal_edi/wizards/document_cancel_wizard.xml
odoo/addons/l10n_br_fiscal_edi/wizards/document_correction_wizard.py
odoo/addons/l10n_br_fiscal_edi/wizards/document_correction_wizard.xml
odoo14_addon_l10n_br_fiscal_edi-14.0.1.4.0.dist-info/METADATA
odoo14_addon_l10n_br_fiscal_edi-14.0.1.4.0.dist-info/WHEEL
odoo14_addon_l10n_br_fiscal_edi-14.0.1.4.0.dist-info/top_level.txt
odoo14_addon_l10n_br_fiscal_edi-14.0.1.4.0.dist-info/RECORD
